{
  "schema_name": "PipelineRun",
  "schema_version": "1.0.0",
  "run_id": "0d857cb9-9d7e-4b21-b3b5-d77e656f3382",
  "parcel_id": "po2-draper-r3-03",
  "zoning_result": {
    "schema_name": "ZoningRules",
    "schema_version": "1.0.0",
    "parcel_id": "po2-draper-r3-03",
    "jurisdiction": "Draper",
    "district": "R3",
    "district_id": null,
    "description": null,
    "overlays": [],
    "standards": [
      {
        "id": "R3:min_lot_size_sqft",
        "district_id": null,
        "standard_type": "min_lot_size_sqft",
        "value": 13000.0,
        "units": "sqft",
        "conditions": [],
        "citation": null,
        "metadata": {
          "source_engine": "zoning_data_scraper",
          "source_run_id": "/Users/arench/Desktop/land-intelligence-workspace/zoning_data_scraper/zoning_dataset_v7/draper",
          "observed_at": "2026-03-20T21:05:37.981719Z"
        }
      },
      {
        "id": "R3:max_units_per_acre",
        "district_id": null,
        "standard_type": "max_units_per_acre",
        "value": 4.0,
        "units": "du/ac",
        "conditions": [],
        "citation": null,
        "metadata": {
          "source_engine": "zoning_data_scraper",
          "source_run_id": "/Users/arench/Desktop/land-intelligence-workspace/zoning_data_scraper/zoning_dataset_v7/draper",
          "observed_at": "2026-03-20T21:05:37.981719Z"
        }
      },
      {
        "id": "R3:height_limit_ft",
        "district_id": null,
        "standard_type": "height_limit_ft",
        "value": 35.0,
        "units": "ft",
        "conditions": [],
        "citation": null,
        "metadata": {
          "source_engine": "zoning_data_scraper",
          "source_run_id": "/Users/arench/Desktop/land-intelligence-workspace/zoning_data_scraper/zoning_dataset_v7/draper",
          "observed_at": "2026-03-20T21:05:37.981719Z"
        }
      },
      {
        "id": "R3:lot_coverage_max",
        "district_id": null,
        "standard_type": "lot_coverage_max",
        "value": 0.45,
        "units": null,
        "conditions": [],
        "citation": null,
        "metadata": {
          "source_engine": "zoning_data_scraper",
          "source_run_id": "/Users/arench/Desktop/land-intelligence-workspace/zoning_data_scraper/zoning_dataset_v7/draper",
          "observed_at": "2026-03-20T21:05:37.981719Z"
        }
      },
      {
        "id": "R3:front_setback_ft",
        "district_id": null,
        "standard_type": "front_setback_ft",
        "value": 25.0,
        "units": "ft",
        "conditions": [],
        "citation": null,
        "metadata": {
          "source_engine": "zoning_data_scraper",
          "source_run_id": "/Users/arench/Desktop/land-intelligence-workspace/zoning_data_scraper/zoning_dataset_v7/draper",
          "observed_at": "2026-03-20T21:05:37.981719Z"
        }
      },
      {
        "id": "R3:side_setback_ft",
        "district_id": null,
        "standard_type": "side_setback_ft",
        "value": 10.0,
        "units": "ft",
        "conditions": [],
        "citation": null,
        "metadata": {
          "source_engine": "zoning_data_scraper",
          "source_run_id": "/Users/arench/Desktop/land-intelligence-workspace/zoning_data_scraper/zoning_dataset_v7/draper",
          "observed_at": "2026-03-20T21:05:37.981719Z"
        }
      },
      {
        "id": "R3:rear_setback_ft",
        "district_id": null,
        "standard_type": "rear_setback_ft",
        "value": 20.0,
        "units": "ft",
        "conditions": [],
        "citation": null,
        "metadata": {
          "source_engine": "zoning_data_scraper",
          "source_run_id": "/Users/arench/Desktop/land-intelligence-workspace/zoning_data_scraper/zoning_dataset_v7/draper",
          "observed_at": "2026-03-20T21:05:37.981719Z"
        }
      }
    ],
    "setbacks": {
      "front": 25.0,
      "side": 10.0,
      "rear": 20.0
    },
    "min_lot_size_sqft": 13000.0,
    "max_units_per_acre": 4.0,
    "height_limit_ft": 35.0,
    "lot_coverage_max": 0.45,
    "min_frontage_ft": null,
    "road_right_of_way_ft": null,
    "allowed_uses": [
      "single_family_residential"
    ],
    "citations": [],
    "metadata": {
      "source_engine": "zoning_data_scraper",
      "source_run_id": "/Users/arench/Desktop/land-intelligence-workspace/zoning_data_scraper/zoning_dataset_v7/draper",
      "observed_at": "2026-03-20T21:05:37.981719Z"
    }
  },
  "layout_result": {
    "schema_name": "LayoutResult",
    "schema_version": "1.0.0",
    "layout_id": "layout-po2-draper-r3-03-83ea37fd7aac",
    "parcel_id": "po2-draper-r3-03",
    "unit_count": 32,
    "road_length_ft": 4266.7,
    "lot_geometries": [
      {
        "type": "Polygon",
        "coordinates": [
          [
            [
              -111.87428719076495,
              40.51773779566172
            ],
            [
              -111.87428719076495,
              40.51718570774963
            ],
            [
              -111.87454739031497,
              40.51718570774963
            ],
            [
              -111.87454739031497,
              40.51773779566172
            ],
            [
              -111.87428719076495,
              40.51773779566172
            ]
          ]
        ]
      },
      {
        "type": "Polygon",
        "coordinates": [
          [
            [
              -111.87417154652049,
              40.51961383961777
            ],
            [
              -111.87417154652049,
              40.52016592752986
            ],
            [
              -111.87391134697046,
              40.52016592752986
            ],
            [
              -111.87391134697046,
              40.51961383961777
            ],
            [
              -111.87417154652049,
              40.51961383961777
            ]
          ]
        ]
      },
      {
        "type": "Polygon",
        "coordinates": [
          [
            [
              -111.87568481333714,
              40.51782570774964
            ],
            [
              -111.87568481333714,
              40.51802350994743
            ],
            [
              -111.87496612569653,
              40.51802350994743
            ],
            [
              -111.87496612569653,
              40.51782570774964
            ],
            [
              -111.87568481333714,
              40.51782570774964
            ]
          ]
        ]
      },
      {
        "type": "Polygon",
        "coordinates": [
          [
            [
              -111.87496612569653,
              40.51773779566172
            ],
            [
              -111.87496612569653,
              40.51753999346392
            ],
            [
              -111.87568481333714,
              40.51753999346392
            ],
            [
              -111.87568481333714,
              40.51773779566172
            ],
            [
              -111.87496612569653,
              40.51773779566172
            ]
          ]
        ]
      },
      {
        "type": "Polygon",
        "coordinates": [
          [
            [
              -111.8734926115889,
              40.51782570774964
            ],
            [
              -111.8734926115889,
              40.51802350994743
            ],
            [
              -111.87277392394829,
              40.51802350994743
            ],
            [
              -111.87277392394829,
              40.51782570774964
            ],
            [
              -111.8734926115889,
              40.51782570774964
            ]
          ]
        ]
      },
      {
        "type": "Polygon",
        "coordinates": [
          [
            [
              -111.87277392394829,
              40.51773779566172
            ],
            [
              -111.87277392394829,
              40.51753999346392
            ],
            [
              -111.8734926115889,
              40.51753999346392
            ],
            [
              -111.8734926115889,
              40.51773779566172
            ],
            [
              -111.87277392394829,
              40.51773779566172
            ]
          ]
        ]
      },
      {
        "type": "Polygon",
        "coordinates": [
          [
            [
              -111.87568481333714,
              40.51842175170568
            ],
            [
              -111.87568481333714,
              40.518619553903484
            ],
            [
              -111.87496612569653,
              40.518619553903484
            ],
            [
              -111.87496612569653,
              40.51842175170568
            ],
            [
              -111.87568481333714,
              40.51842175170568
            ]
          ]
        ]
      },
      {
        "type": "Polygon",
        "coordinates": [
          [
            [
              -111.87496612569653,
              40.51833383961777
            ],
            [
              -111.87496612569653,
              40.518136037419964
            ],
            [
              -111.87568481333714,
              40.518136037419964
            ],
            [
              -111.87568481333714,
              40.51833383961777
            ],
            [
              -111.87496612569653,
              40.51833383961777
            ]
          ]
        ]
      },
      {
        "type": "Polygon",
        "coordinates": [
          [
            [
              -111.8734926115889,
              40.51842175170568
            ],
            [
              -111.8734926115889,
              40.518619553903484
            ],
            [
              -111.87277392394829,
              40.518619553903484
            ],
            [
              -111.87277392394829,
              40.51842175170568
            ],
            [
              -111.8734926115889,
              40.51842175170568
            ]
          ]
        ]
      },
      {
        "type": "Polygon",
        "coordinates": [
          [
            [
              -111.87277392394829,
              40.51833383961777
            ],
            [
              -111.87277392394829,
              40.518136037419964
            ],
            [
              -111.8734926115889,
              40.518136037419964
            ],
            [
              -111.8734926115889,
              40.51833383961777
            ],
            [
              -111.87277392394829,
              40.51833383961777
            ]
          ]
        ]
      },
      {
        "type": "Polygon",
        "coordinates": [
          [
            [
              -111.87568481333714,
              40.519017795661725
            ],
            [
              -111.87568481333714,
              40.51921559785953
            ],
            [
              -111.87496612569653,
              40.51921559785953
            ],
            [
              -111.87496612569653,
              40.519017795661725
            ],
            [
              -111.87568481333714,
              40.519017795661725
            ]
          ]
        ]
      },
      {
        "type": "Polygon",
        "coordinates": [
          [
            [
              -111.87496612569653,
              40.51892988357381
            ],
            [
              -111.87496612569653,
              40.51873208137601
            ],
            [
              -111.87568481333714,
              40.51873208137601
            ],
            [
              -111.87568481333714,
              40.51892988357381
            ],
            [
              -111.87496612569653,
              40.51892988357381
            ]
          ]
        ]
      },
      {
        "type": "Polygon",
        "coordinates": [
          [
            [
              -111.8734926115889,
              40.519017795661725
            ],
            [
              -111.8734926115889,
              40.51921559785953
            ],
            [
              -111.87277392394829,
              40.51921559785953
            ],
            [
              -111.87277392394829,
              40.519017795661725
            ],
            [
              -111.8734926115889,
              40.519017795661725
            ]
          ]
        ]
      },
      {
        "type": "Polygon",
        "coordinates": [
          [
            [
              -111.87277392394829,
              40.51892988357381
            ],
            [
              -111.87277392394829,
              40.51873208137601
            ],
            [
              -111.8734926115889,
              40.51873208137601
            ],
            [
              -111.8734926115889,
              40.51892988357381
            ],
            [
              -111.87277392394829,
              40.51892988357381
            ]
          ]
        ]
      },
      {
        "type": "Polygon",
        "coordinates": [
          [
            [
              -111.87568481333714,
              40.51961383961777
            ],
            [
              -111.87568481333714,
              40.51981164181557
            ],
            [
              -111.87496612569653,
              40.51981164181557
            ],
            [
              -111.87496612569653,
              40.51961383961777
            ],
            [
              -111.87568481333714,
              40.51961383961777
            ]
          ]
        ]
      },
      {
        "type": "Polygon",
        "coordinates": [
          [
            [
              -111.87496612569653,
              40.519525927529855
            ],
            [
              -111.87496612569653,
              40.51932812533206
            ],
            [
              -111.87568481333714,
              40.51932812533206
            ],
            [
              -111.87568481333714,
              40.519525927529855
            ],
            [
              -111.87496612569653,
              40.519525927529855
            ]
          ]
        ]
      },
      {
        "type": "Polygon",
        "coordinates": [
          [
            [
              -111.8734926115889,
              40.51961383961777
            ],
            [
              -111.8734926115889,
              40.51981164181557
            ],
            [
              -111.87277392394829,
              40.51981164181557
            ],
            [
              -111.87277392394829,
              40.51961383961777
            ],
            [
              -111.8734926115889,
              40.51961383961777
            ]
          ]
        ]
      },
      {
        "type": "Polygon",
        "coordinates": [
          [
            [
              -111.87277392394829,
              40.519525927529855
            ],
            [
              -111.87277392394829,
              40.51932812533206
            ],
            [
              -111.8734926115889,
              40.51932812533206
            ],
            [
              -111.8734926115889,
              40.519525927529855
            ],
            [
              -111.87277392394829,
              40.519525927529855
            ]
          ]
        ]
      },
      {
        "type": "Polygon",
        "coordinates": [
          [
            [
              -111.87428719076495,
              40.51782570774964
            ],
            [
              -111.87496612569653,
              40.51782570774964
            ],
            [
              -111.87496612569653,
              40.51802350994743
            ],
            [
              -111.87428719076495,
              40.51802350994743
            ],
            [
              -111.87428719076495,
              40.51782570774964
            ]
          ]
        ]
      },
      {
        "type": "Polygon",
        "coordinates": [
          [
            [
              -111.87417154652049,
              40.51782570774964
            ],
            [
              -111.87417154652049,
              40.51802350994743
            ],
            [
              -111.8734926115889,
              40.51802350994743
            ],
            [
              -111.8734926115889,
              40.51782570774964
            ],
            [
              -111.87417154652049,
              40.51782570774964
            ]
          ]
        ]
      },
      {
        "type": "Polygon",
        "coordinates": [
          [
            [
              -111.87417154652049,
              40.51773779566172
            ],
            [
              -111.8734926115889,
              40.51773779566172
            ],
            [
              -111.8734926115889,
              40.51753999346392
            ],
            [
              -111.87417154652049,
              40.51753999346392
            ],
            [
              -111.87417154652049,
              40.51773779566172
            ]
          ]
        ]
      },
      {
        "type": "Polygon",
        "coordinates": [
          [
            [
              -111.87428719076495,
              40.51842175170568
            ],
            [
              -111.87496612569653,
              40.51842175170568
            ],
            [
              -111.87496612569653,
              40.518619553903484
            ],
            [
              -111.87428719076495,
              40.518619553903484
            ],
            [
              -111.87428719076495,
              40.51842175170568
            ]
          ]
        ]
      },
      {
        "type": "Polygon",
        "coordinates": [
          [
            [
              -111.87428719076495,
              40.51833383961777
            ],
            [
              -111.87428719076495,
              40.518136037419964
            ],
            [
              -111.87496612569653,
              40.518136037419964
            ],
            [
              -111.87496612569653,
              40.51833383961777
            ],
            [
              -111.87428719076495,
              40.51833383961777
            ]
          ]
        ]
      },
      {
        "type": "Polygon",
        "coordinates": [
          [
            [
              -111.87417154652049,
              40.51842175170568
            ],
            [
              -111.87417154652049,
              40.518619553903484
            ],
            [
              -111.8734926115889,
              40.518619553903484
            ],
            [
              -111.8734926115889,
              40.51842175170568
            ],
            [
              -111.87417154652049,
              40.51842175170568
            ]
          ]
        ]
      },
      {
        "type": "Polygon",
        "coordinates": [
          [
            [
              -111.87417154652049,
              40.51833383961777
            ],
            [
              -111.8734926115889,
              40.51833383961777
            ],
            [
              -111.8734926115889,
              40.518136037419964
            ],
            [
              -111.87417154652049,
              40.518136037419964
            ],
            [
              -111.87417154652049,
              40.51833383961777
            ]
          ]
        ]
      },
      {
        "type": "Polygon",
        "coordinates": [
          [
            [
              -111.87428719076495,
              40.519017795661725
            ],
            [
              -111.87496612569653,
              40.519017795661725
            ],
            [
              -111.87496612569653,
              40.51921559785953
            ],
            [
              -111.87428719076495,
              40.51921559785953
            ],
            [
              -111.87428719076495,
              40.519017795661725
            ]
          ]
        ]
      },
      {
        "type": "Polygon",
        "coordinates": [
          [
            [
              -111.87428719076495,
              40.51892988357381
            ],
            [
              -111.87428719076495,
              40.51873208137601
            ],
            [
              -111.87496612569653,
              40.51873208137601
            ],
            [
              -111.87496612569653,
              40.51892988357381
            ],
            [
              -111.87428719076495,
              40.51892988357381
            ]
          ]
        ]
      },
      {
        "type": "Polygon",
        "coordinates": [
          [
            [
              -111.87417154652049,
              40.519017795661725
            ],
            [
              -111.87417154652049,
              40.51921559785953
            ],
            [
              -111.8734926115889,
              40.51921559785953
            ],
            [
              -111.8734926115889,
              40.519017795661725
            ],
            [
              -111.87417154652049,
              40.519017795661725
            ]
          ]
        ]
      },
      {
        "type": "Polygon",
        "coordinates": [
          [
            [
              -111.87417154652049,
              40.51892988357381
            ],
            [
              -111.8734926115889,
              40.51892988357381
            ],
            [
              -111.8734926115889,
              40.51873208137601
            ],
            [
              -111.87417154652049,
              40.51873208137601
            ],
            [
              -111.87417154652049,
              40.51892988357381
            ]
          ]
        ]
      },
      {
        "type": "Polygon",
        "coordinates": [
          [
            [
              -111.87428719076495,
              40.51961383961777
            ],
            [
              -111.87496612569653,
              40.51961383961777
            ],
            [
              -111.87496612569653,
              40.51981164181557
            ],
            [
              -111.87428719076495,
              40.51981164181557
            ],
            [
              -111.87428719076495,
              40.51961383961777
            ]
          ]
        ]
      },
      {
        "type": "Polygon",
        "coordinates": [
          [
            [
              -111.87428719076495,
              40.519525927529855
            ],
            [
              -111.87428719076495,
              40.51932812533206
            ],
            [
              -111.87496612569653,
              40.51932812533206
            ],
            [
              -111.87496612569653,
              40.519525927529855
            ],
            [
              -111.87428719076495,
              40.519525927529855
            ]
          ]
        ]
      },
      {
        "type": "Polygon",
        "coordinates": [
          [
            [
              -111.87417154652049,
              40.519525927529855
            ],
            [
              -111.8734926115889,
              40.519525927529855
            ],
            [
              -111.8734926115889,
              40.51932812533206
            ],
            [
              -111.87417154652049,
              40.51932812533206
            ],
            [
              -111.87417154652049,
              40.519525927529855
            ]
          ]
        ]
      }
    ],
    "road_geometries": [
      {
        "type": "LineString",
        "coordinates": [
          [
            -111.87422936864272,
            40.51718570774963
          ],
          [
            -111.87422936864272,
            40.52016592752986
          ]
        ]
      },
      {
        "type": "LineString",
        "coordinates": [
          [
            -111.87568481333714,
            40.51778175170568
          ],
          [
            -111.87424743805592,
            40.51778175170568
          ]
        ]
      },
      {
        "type": "LineString",
        "coordinates": [
          [
            -111.87421129922951,
            40.51778175170568
          ],
          [
            -111.87277392394829,
            40.51778175170568
          ]
        ]
      },
      {
        "type": "LineString",
        "coordinates": [
          [
            -111.87568481333714,
            40.51837779566172
          ],
          [
            -111.87424743805592,
            40.51837779566172
          ]
        ]
      },
      {
        "type": "LineString",
        "coordinates": [
          [
            -111.87421129922951,
            40.51837779566172
          ],
          [
            -111.87277392394829,
            40.51837779566172
          ]
        ]
      },
      {
        "type": "LineString",
        "coordinates": [
          [
            -111.87568481333714,
            40.51897383961777
          ],
          [
            -111.87424743805592,
            40.51897383961777
          ]
        ]
      },
      {
        "type": "LineString",
        "coordinates": [
          [
            -111.87421129922951,
            40.51897383961777
          ],
          [
            -111.87277392394829,
            40.51897383961777
          ]
        ]
      },
      {
        "type": "LineString",
        "coordinates": [
          [
            -111.87568481333714,
            40.519569883573816
          ],
          [
            -111.87424743805592,
            40.519569883573816
          ]
        ]
      },
      {
        "type": "LineString",
        "coordinates": [
          [
            -111.87421129922951,
            40.519569883573816
          ],
          [
            -111.87277392394829,
            40.519569883573816
          ]
        ]
      }
    ],
    "open_space_area_sqft": 1037462.959995558,
    "utility_length_ft": 0.0,
    "score": null,
    "buildable_area_sqft": null,
    "metadata": {
      "source_engine": "bedrock.layout_service",
      "source_run_id": null,
      "observed_at": "2026-03-20T21:05:38.004341Z"
    }
  },
  "feasibility_result": {
    "schema_name": "FeasibilityResult",
    "schema_version": "1.0.0",
    "scenario_id": "afd60e40-ad1d-564b-bf89-11c36710e99f",
    "layout_id": "layout-po2-draper-r3-03-83ea37fd7aac",
    "parcel_id": "po2-draper-r3-03",
    "units": 32,
    "estimated_home_price": 480000.0,
    "construction_cost_per_home": 445120.0,
    "development_cost_total": 1948714.7024793387,
    "projected_revenue": 15360000.0,
    "projected_cost": 16192554.702479338,
    "projected_profit": -832554.7024793383,
    "ROI": -0.0514158956246639,
    "profit_margin": -0.05420278010933192,
    "revenue_per_unit": 480000.0,
    "cost_per_unit": 506017.3344524793,
    "rank": null,
    "risk_score": 0.6921212191899118,
    "requested_units": null,
    "constraint_violations": [
      "projected_profit_negative"
    ],
    "confidence": 0.9,
    "status": "constrained",
    "financial_summary": {
      "units": 32,
      "estimated_home_price": 480000.0,
      "construction_cost_per_home": 445120.0,
      "road_cost_per_ft": 300.0,
      "road_length": 4266.7,
      "land_cost": 0.0,
      "projected_revenue": 15360000.0,
      "development_cost_total": 1948714.7024793387,
      "projected_cost": 16192554.702479338,
      "projected_profit": -832554.7024793383,
      "ROI": -0.0514158956246639,
      "development_cost_breakdown": {
        "roads": 1280010.0,
        "utilities": 0.0,
        "grading": 128001.0,
        "sitework": 428703.70247933886,
        "permitting": 112000.0
      },
      "profit_margin": -0.05420278010933192,
      "revenue_per_unit": 480000.0,
      "cost_per_unit": 506017.3344524793
    },
    "explanation": {
      "primary_driver": "road_cost",
      "cost_breakdown": {
        "construction": 14243840.0,
        "development": 1948714.7024793387
      },
      "revenue_breakdown": {
        "units": 32,
        "price_per_home": 480000.0
      }
    },
    "assumptions": {
      "used_default_estimated_home_price": true,
      "used_default_construction_cost_per_home": true,
      "used_default_road_cost_per_ft": true,
      "used_default_land_price": true,
      "used_default_soft_cost_factor": true
    },
    "metadata": null
  },
  "timestamp": "2026-03-20T21:05:38.004631Z",
  "git_commit": "ceaa51d8bb6aa1d29cf293e8e9dd47cbc86f6c8e",
  "input_hash": "662fe7fb1b0d5ee6a0e1ac329cd97a64433c88a45c381d5679c7d70b2affb4ba",
  "stage_runtimes": {
    "parcel.load": 0.000167,
    "zoning.lookup": 0.00359,
    "layout.search": 0.022409,
    "feasibility.evaluate": 0.000218
  }
}