{
  "schema_name": "PipelineRun",
  "schema_version": "1.0.0",
  "run_id": "159dcf32-7bf3-467d-979d-c96ba35b7ba2",
  "status": "completed",
  "parcel_id": "ut-salt-lake-72089",
  "zoning_result": {
    "schema_name": "ZoningRules",
    "schema_version": "1.0.0",
    "parcel_id": "ut-salt-lake-72089",
    "jurisdiction": "West Valley City",
    "district": "R-1-7000",
    "district_id": null,
    "description": null,
    "overlays": [],
    "standards": [
      {
        "id": "R-1-7000:min_lot_size_sqft",
        "district_id": null,
        "standard_type": "min_lot_size_sqft",
        "value": 7000.0,
        "units": "sqft",
        "conditions": [],
        "citation": null,
        "metadata": {
          "source_engine": "zoning_data_scraper",
          "source_run_id": "jurisdiction_fallback",
          "observed_at": "2026-03-26T23:44:26.313236Z"
        }
      },
      {
        "id": "R-1-7000:max_units_per_acre",
        "district_id": null,
        "standard_type": "max_units_per_acre",
        "value": 6.22,
        "units": "du/ac",
        "conditions": [],
        "citation": null,
        "metadata": {
          "source_engine": "zoning_data_scraper",
          "source_run_id": "jurisdiction_fallback",
          "observed_at": "2026-03-26T23:44:26.313236Z"
        }
      },
      {
        "id": "R-1-7000:height_limit_ft",
        "district_id": null,
        "standard_type": "height_limit_ft",
        "value": 35.0,
        "units": "ft",
        "conditions": [],
        "citation": null,
        "metadata": {
          "source_engine": "zoning_data_scraper",
          "source_run_id": "jurisdiction_fallback",
          "observed_at": "2026-03-26T23:44:26.313236Z"
        }
      },
      {
        "id": "R-1-7000:lot_coverage_max",
        "district_id": null,
        "standard_type": "lot_coverage_max",
        "value": 0.45,
        "units": null,
        "conditions": [],
        "citation": null,
        "metadata": {
          "source_engine": "zoning_data_scraper",
          "source_run_id": "jurisdiction_fallback",
          "observed_at": "2026-03-26T23:44:26.313236Z"
        }
      },
      {
        "id": "R-1-7000:min_frontage_ft",
        "district_id": null,
        "standard_type": "min_frontage_ft",
        "value": 50.0,
        "units": "ft",
        "conditions": [],
        "citation": null,
        "metadata": {
          "source_engine": "zoning_data_scraper",
          "source_run_id": "jurisdiction_fallback",
          "observed_at": "2026-03-26T23:44:26.313236Z"
        }
      },
      {
        "id": "R-1-7000:front_setback_ft",
        "district_id": null,
        "standard_type": "front_setback_ft",
        "value": 25.0,
        "units": "ft",
        "conditions": [],
        "citation": null,
        "metadata": {
          "source_engine": "zoning_data_scraper",
          "source_run_id": "jurisdiction_fallback",
          "observed_at": "2026-03-26T23:44:26.313236Z"
        }
      },
      {
        "id": "R-1-7000:side_setback_ft",
        "district_id": null,
        "standard_type": "side_setback_ft",
        "value": 8.0,
        "units": "ft",
        "conditions": [],
        "citation": null,
        "metadata": {
          "source_engine": "zoning_data_scraper",
          "source_run_id": "jurisdiction_fallback",
          "observed_at": "2026-03-26T23:44:26.313236Z"
        }
      },
      {
        "id": "R-1-7000:rear_setback_ft",
        "district_id": null,
        "standard_type": "rear_setback_ft",
        "value": 20.0,
        "units": "ft",
        "conditions": [],
        "citation": null,
        "metadata": {
          "source_engine": "zoning_data_scraper",
          "source_run_id": "jurisdiction_fallback",
          "observed_at": "2026-03-26T23:44:26.313236Z"
        }
      }
    ],
    "setbacks": {
      "front": 25.0,
      "side": 8.0,
      "rear": 20.0
    },
    "min_lot_size_sqft": 7000.0,
    "max_units_per_acre": 6.22,
    "height_limit_ft": 35.0,
    "lot_coverage_max": 0.45,
    "min_frontage_ft": 50.0,
    "road_right_of_way_ft": null,
    "allowed_uses": [
      "single_family_residential"
    ],
    "citations": [],
    "metadata": {
      "source_engine": "zoning_data_scraper",
      "source_run_id": "jurisdiction_fallback",
      "observed_at": "2026-03-26T23:44:26.313236Z"
    }
  },
  "layout_result": {
    "schema_name": "LayoutResult",
    "schema_version": "1.0.0",
    "layout_id": "layout-ut-salt-lake-72089-6e530d9ea879",
    "parcel_id": "ut-salt-lake-72089",
    "unit_count": 2,
    "road_length_ft": 363.4,
    "lot_geometries": [
      {
        "type": "Polygon",
        "coordinates": [
          [
            [
              -111.946689,
              40.685741
            ],
            [
              -111.94662,
              40.685651
            ],
            [
              -111.946689,
              40.685621
            ],
            [
              -111.946596,
              40.6855
            ],
            [
              -111.946596,
              40.68539
            ],
            [
              -111.947049,
              40.68539
            ],
            [
              -111.947049,
              40.685751
            ],
            [
              -111.946665,
              40.685751
            ],
            [
              -111.946689,
              40.685741
            ]
          ]
        ]
      },
      {
        "type": "Polygon",
        "coordinates": [
          [
            [
              -111.94649,
              40.6855
            ],
            [
              -111.946398,
              40.685621
            ],
            [
              -111.946466,
              40.685651
            ],
            [
              -111.946398,
              40.685741
            ],
            [
              -111.946421,
              40.685751
            ],
            [
              -111.946037,
              40.685751
            ],
            [
              -111.946037,
              40.68539
            ],
            [
              -111.94649,
              40.68539
            ],
            [
              -111.94649,
              40.6855
            ]
          ]
        ]
      }
    ],
    "road_geometries": [
      {
        "type": "LineString",
        "coordinates": [
          [
            -111.946543,
            40.68551
          ],
          [
            -111.946642,
            40.685641
          ]
        ]
      },
      {
        "type": "LineString",
        "coordinates": [
          [
            -111.946543,
            40.685631
          ],
          [
            -111.946642,
            40.685761
          ]
        ]
      },
      {
        "type": "LineString",
        "coordinates": [
          [
            -111.946543,
            40.685356
          ],
          [
            -111.946543,
            40.68539
          ]
        ]
      },
      {
        "type": "LineString",
        "coordinates": [
          [
            -111.946543,
            40.68539
          ],
          [
            -111.946543,
            40.685751
          ]
        ]
      },
      {
        "type": "LineString",
        "coordinates": [
          [
            -111.946543,
            40.68551
          ],
          [
            -111.946444,
            40.685641
          ]
        ]
      },
      {
        "type": "LineString",
        "coordinates": [
          [
            -111.946543,
            40.685631
          ],
          [
            -111.946444,
            40.685761
          ]
        ]
      }
    ],
    "open_space_area_sqft": 43971.17999969972,
    "utility_length_ft": 0.0,
    "score": null,
    "buildable_area_sqft": null,
    "metadata": {
      "source_engine": "bedrock.layout_service",
      "source_run_id": null,
      "observed_at": "2026-03-26T23:44:26.611584Z"
    }
  },
  "feasibility_result": {
    "schema_name": "FeasibilityResult",
    "schema_version": "1.0.0",
    "scenario_id": "50bc0668-037c-5f07-8953-942b5df28695",
    "layout_id": "layout-ut-salt-lake-72089-6e530d9ea879",
    "parcel_id": "ut-salt-lake-72089",
    "units": 2,
    "estimated_home_price": 670560.0,
    "price_per_sqft": 209.55,
    "estimated_home_size_sqft": 3200.0,
    "construction_cost_per_sqft": 131.1284,
    "construction_cost_per_home": 671377.408,
    "development_cost_total": 146132.83205090908,
    "projected_revenue": 1341120.0,
    "projected_cost": 1610727.7904509092,
    "projected_profit": -269607.7904509092,
    "ROI": -0.16738259068308173,
    "ROI_base": -0.16738259068308173,
    "ROI_best_case": -0.010984576495673058,
    "ROI_worst_case": -0.3034194096507885,
    "break_even_price": 805363.8952254546,
    "profit_margin": -0.2010318170267457,
    "revenue_per_unit": 670560.0,
    "cost_per_unit": 805363.8952254546,
    "rank": null,
    "risk_score": 0.7404336529269792,
    "requested_units": null,
    "constraint_violations": [
      "projected_profit_negative"
    ],
    "confidence": 0.73,
    "key_risk_factors": [
      "above_national_cost_region",
      "negative_or_unknown_base_roi",
      "high_road_length_per_unit"
    ],
    "status": "constrained",
    "financial_summary": {
      "units": 2,
      "estimated_home_price": 670560.0,
      "construction_cost_per_home": 671377.408,
      "road_cost_per_ft": 302.604,
      "road_length": 363.4,
      "land_cost": 121840.1424,
      "projected_revenue": 1341120.0,
      "development_cost_total": 146132.83205090908,
      "projected_cost": 1610727.7904509092,
      "projected_profit": -269607.7904509092,
      "ROI": -0.16738259068308173,
      "price_per_sqft": 209.55,
      "estimated_home_size_sqft": 3200.0,
      "construction_cost_per_sqft": 131.1284,
      "ROI_base": -0.16738259068308173,
      "ROI_best_case": -0.010984576495673058,
      "ROI_worst_case": -0.3034194096507885,
      "break_even_price": 805363.8952254546,
      "confidence_score": 0.73,
      "key_risk_factors": [
        "above_national_cost_region",
        "negative_or_unknown_base_roi",
        "high_road_length_per_unit"
      ],
      "market_context": {
        "jurisdiction": "West Valley City",
        "county_name": "Salt Lake County, Utah",
        "median_home_value": 419100.0,
        "rpp_all_items": 100.868,
        "reference_home_size_sqft": 2000.0,
        "baseline_cost_per_sqft": 130.0,
        "baseline_road_cost_per_ft": 300.0,
        "land_value_share_of_home_value": 0.18,
        "price_reference_date": "2024-01-01",
        "msa_name": "Salt Lake City MSA",
        "sources": {
          "census_acs_2024_place_median_home_value": "https://api.census.gov/data/2024/acs/acs5?get=NAME,B25077_001E&for=place:*&in=state:49",
          "census_acs_2024_county_median_home_value": "https://api.census.gov/data/2024/acs/acs5?get=NAME,B25077_001E&for=county:*&in=state:49",
          "fred_rpp_salt_lake_city_msa": "https://fred.stlouisfed.org/graph/fredgraph.csv?id=RPPALL41620",
          "fred_rpp_provo_orem_msa": "https://fred.stlouisfed.org/graph/fredgraph.csv?id=RPPALL39340"
        },
        "used_county_fallback": false,
        "estimated_home_size_sqft": 3200.0,
        "price_per_sqft": 209.55,
        "construction_cost_per_sqft": 131.1284,
        "road_cost_per_ft": 302.604,
        "land_price_estimate": 121840.1424,
        "pricing_proxy": "acs_median_home_value_per_reference_home_size",
        "cost_proxy": "bea_rpp_scaled_baseline_costs"
      },
      "development_cost_breakdown": {
        "roads": 109966.29359999999,
        "utilities": 0.0,
        "grading": 10996.629359999999,
        "sitework": 18169.909090909092,
        "permitting": 7000.0
      },
      "profit_margin": -0.2010318170267457,
      "revenue_per_unit": 670560.0,
      "cost_per_unit": 805363.8952254546
    },
    "explanation": {
      "primary_driver": "home_price",
      "cost_breakdown": {
        "construction": 1342754.816,
        "development": 146132.83205090908
      },
      "revenue_breakdown": {
        "units": 2,
        "price_per_home": 670560.0
      }
    },
    "assumptions": {
      "used_default_estimated_home_price": false,
      "used_default_construction_cost_per_home": false,
      "used_default_road_cost_per_ft": false,
      "used_default_land_price": false,
      "used_default_soft_cost_factor": false,
      "market_sources": {
        "census_acs_2024_place_median_home_value": "https://api.census.gov/data/2024/acs/acs5?get=NAME,B25077_001E&for=place:*&in=state:49",
        "census_acs_2024_county_median_home_value": "https://api.census.gov/data/2024/acs/acs5?get=NAME,B25077_001E&for=county:*&in=state:49",
        "fred_rpp_salt_lake_city_msa": "https://fred.stlouisfed.org/graph/fredgraph.csv?id=RPPALL41620",
        "fred_rpp_provo_orem_msa": "https://fred.stlouisfed.org/graph/fredgraph.csv?id=RPPALL39340"
      }
    },
    "metadata": null
  },
  "near_feasible_result": null,
  "timestamp": "2026-03-26T23:44:26.611907Z",
  "git_commit": "05222bb8c8c582cae630ed93bacc9765ba243990",
  "input_hash": "c75b3385df41082654f058156067f869763cecc12b0a9101634130005ebe6525",
  "stage_runtimes": {
    "parcel.load": 0.001002,
    "zoning.lookup": 0.019366,
    "layout.search": 0.298076,
    "feasibility.evaluate": 0.000268
  },
  "zoning_bypassed": false,
  "bypass_reason": null
}