{
  "schema_name": "PipelineRun",
  "schema_version": "1.0.0",
  "run_id": "1d893c20-fbe0-4d66-9bcd-556a183524e7",
  "parcel_id": "exp-lehi-007-determinism-1",
  "zoning_result": {
    "schema_name": "ZoningRules",
    "schema_version": "1.0.0",
    "parcel_id": "exp-lehi-007-determinism-1",
    "jurisdiction": "Lehi",
    "district": "TH-5",
    "district_id": null,
    "description": null,
    "overlays": [],
    "standards": [
      {
        "id": "TH-5:min_lot_size_sqft",
        "district_id": null,
        "standard_type": "min_lot_size_sqft",
        "value": 6000.0,
        "units": "sqft",
        "conditions": [],
        "citation": null,
        "metadata": {
          "source_engine": "zoning_data_scraper",
          "source_run_id": "/Users/arench/Desktop/land-intelligence-workspace/zoning_data_scraper/zoning_dataset_v8/lehi",
          "observed_at": "2026-03-20T17:53:56.264277Z"
        }
      },
      {
        "id": "TH-5:max_units_per_acre",
        "district_id": null,
        "standard_type": "max_units_per_acre",
        "value": 5.0,
        "units": "du/ac",
        "conditions": [],
        "citation": null,
        "metadata": {
          "source_engine": "zoning_data_scraper",
          "source_run_id": "/Users/arench/Desktop/land-intelligence-workspace/zoning_data_scraper/zoning_dataset_v8/lehi",
          "observed_at": "2026-03-20T17:53:56.264277Z"
        }
      },
      {
        "id": "TH-5:height_limit_ft",
        "district_id": null,
        "standard_type": "height_limit_ft",
        "value": 35.0,
        "units": "ft",
        "conditions": [],
        "citation": null,
        "metadata": {
          "source_engine": "zoning_data_scraper",
          "source_run_id": "/Users/arench/Desktop/land-intelligence-workspace/zoning_data_scraper/zoning_dataset_v8/lehi",
          "observed_at": "2026-03-20T17:53:56.264277Z"
        }
      },
      {
        "id": "TH-5:lot_coverage_max",
        "district_id": null,
        "standard_type": "lot_coverage_max",
        "value": 0.5,
        "units": null,
        "conditions": [],
        "citation": null,
        "metadata": {
          "source_engine": "zoning_data_scraper",
          "source_run_id": "/Users/arench/Desktop/land-intelligence-workspace/zoning_data_scraper/zoning_dataset_v8/lehi",
          "observed_at": "2026-03-20T17:53:56.264277Z"
        }
      },
      {
        "id": "TH-5:front_setback_ft",
        "district_id": null,
        "standard_type": "front_setback_ft",
        "value": 25.0,
        "units": "ft",
        "conditions": [],
        "citation": null,
        "metadata": {
          "source_engine": "zoning_data_scraper",
          "source_run_id": "/Users/arench/Desktop/land-intelligence-workspace/zoning_data_scraper/zoning_dataset_v8/lehi",
          "observed_at": "2026-03-20T17:53:56.264277Z"
        }
      },
      {
        "id": "TH-5:side_setback_ft",
        "district_id": null,
        "standard_type": "side_setback_ft",
        "value": 8.0,
        "units": "ft",
        "conditions": [],
        "citation": null,
        "metadata": {
          "source_engine": "zoning_data_scraper",
          "source_run_id": "/Users/arench/Desktop/land-intelligence-workspace/zoning_data_scraper/zoning_dataset_v8/lehi",
          "observed_at": "2026-03-20T17:53:56.264277Z"
        }
      },
      {
        "id": "TH-5:rear_setback_ft",
        "district_id": null,
        "standard_type": "rear_setback_ft",
        "value": 20.0,
        "units": "ft",
        "conditions": [],
        "citation": null,
        "metadata": {
          "source_engine": "zoning_data_scraper",
          "source_run_id": "/Users/arench/Desktop/land-intelligence-workspace/zoning_data_scraper/zoning_dataset_v8/lehi",
          "observed_at": "2026-03-20T17:53:56.264277Z"
        }
      }
    ],
    "setbacks": {
      "front": 25.0,
      "side": 8.0,
      "rear": 20.0
    },
    "min_lot_size_sqft": 6000.0,
    "max_units_per_acre": 5.0,
    "height_limit_ft": 35.0,
    "lot_coverage_max": 0.5,
    "min_frontage_ft": null,
    "road_right_of_way_ft": null,
    "allowed_uses": [
      "townhome",
      "single_family_attached"
    ],
    "citations": [],
    "metadata": {
      "source_engine": "zoning_data_scraper",
      "source_run_id": "/Users/arench/Desktop/land-intelligence-workspace/zoning_data_scraper/zoning_dataset_v8/lehi",
      "observed_at": "2026-03-20T17:53:56.264277Z"
    }
  },
  "layout_result": {
    "schema_name": "LayoutResult",
    "schema_version": "1.0.0",
    "layout_id": "layout-exp-lehi-007-determinism-1-3dbe4eddc3eb",
    "parcel_id": "exp-lehi-007-determinism-1",
    "unit_count": 40,
    "road_length_ft": 2411.5,
    "lot_geometries": [
      {
        "type": "Polygon",
        "coordinates": [
          [
            [
              -111.91802825409489,
              40.43109350723965
            ],
            [
              -111.91828811842618,
              40.43109350723965
            ],
            [
              -111.91828811842618,
              40.431386158338555
            ],
            [
              -111.91802825409489,
              40.431386158338555
            ],
            [
              -111.91802825409489,
              40.43109350723965
            ]
          ]
        ]
      },
      {
        "type": "Polygon",
        "coordinates": [
          [
            [
              -111.91791275883655,
              40.431386158338555
            ],
            [
              -111.91765289450527,
              40.431386158338555
            ],
            [
              -111.91765289450527,
              40.43109350723965
            ],
            [
              -111.91791275883655,
              40.43109350723965
            ],
            [
              -111.91791275883655,
              40.431386158338555
            ]
          ]
        ]
      },
      {
        "type": "Polygon",
        "coordinates": [
          [
            [
              -111.91721073713632,
              40.43160350723965
            ],
            [
              -111.91721073713632,
              40.43180130943745
            ],
            [
              -111.91683987553867,
              40.43180130943745
            ],
            [
              -111.91683987553867,
              40.43160350723965
            ],
            [
              -111.91721073713632,
              40.43160350723965
            ]
          ]
        ]
      },
      {
        "type": "Polygon",
        "coordinates": [
          [
            [
              -111.91683987553867,
              40.43151559515174
            ],
            [
              -111.91683987553867,
              40.43131779295394
            ],
            [
              -111.91721073713632,
              40.43131779295394
            ],
            [
              -111.91721073713632,
              40.43151559515174
            ],
            [
              -111.91683987553867,
              40.43151559515174
            ]
          ]
        ]
      },
      {
        "type": "Polygon",
        "coordinates": [
          [
            [
              -111.91721073713632,
              40.432069551195696
            ],
            [
              -111.91721073713632,
              40.4322673533935
            ],
            [
              -111.91683987553867,
              40.4322673533935
            ],
            [
              -111.91683987553867,
              40.432069551195696
            ],
            [
              -111.91721073713632,
              40.432069551195696
            ]
          ]
        ]
      },
      {
        "type": "Polygon",
        "coordinates": [
          [
            [
              -111.91683987553867,
              40.43198163910778
            ],
            [
              -111.91683987553867,
              40.43178383690998
            ],
            [
              -111.91721073713632,
              40.43178383690998
            ],
            [
              -111.91721073713632,
              40.43198163910778
            ],
            [
              -111.91683987553867,
              40.43198163910778
            ]
          ]
        ]
      },
      {
        "type": "Polygon",
        "coordinates": [
          [
            [
              -111.91910113739277,
              40.43160350723965
            ],
            [
              -111.91910113739277,
              40.43180130943745
            ],
            [
              -111.91873027579513,
              40.43180130943745
            ],
            [
              -111.91873027579513,
              40.43160350723965
            ],
            [
              -111.91910113739277,
              40.43160350723965
            ]
          ]
        ]
      },
      {
        "type": "Polygon",
        "coordinates": [
          [
            [
              -111.91873027579513,
              40.43160350723965
            ],
            [
              -111.91873027579513,
              40.43180130943745
            ],
            [
              -111.91835941419748,
              40.43180130943745
            ],
            [
              -111.91835941419748,
              40.43160350723965
            ],
            [
              -111.91873027579513,
              40.43160350723965
            ]
          ]
        ]
      },
      {
        "type": "Polygon",
        "coordinates": [
          [
            [
              -111.91873027579513,
              40.43151559515174
            ],
            [
              -111.91873027579513,
              40.43131779295394
            ],
            [
              -111.91910113739277,
              40.43131779295394
            ],
            [
              -111.91910113739277,
              40.43151559515174
            ],
            [
              -111.91873027579513,
              40.43151559515174
            ]
          ]
        ]
      },
      {
        "type": "Polygon",
        "coordinates": [
          [
            [
              -111.91835941419748,
              40.43151559515174
            ],
            [
              -111.91835941419748,
              40.43131779295394
            ],
            [
              -111.91873027579513,
              40.43131779295394
            ],
            [
              -111.91873027579513,
              40.43151559515174
            ],
            [
              -111.91835941419748,
              40.43151559515174
            ]
          ]
        ]
      },
      {
        "type": "Polygon",
        "coordinates": [
          [
            [
              -111.91758159873396,
              40.43160350723965
            ],
            [
              -111.91758159873396,
              40.43180130943745
            ],
            [
              -111.91721073713632,
              40.43180130943745
            ],
            [
              -111.91721073713632,
              40.43160350723965
            ],
            [
              -111.91758159873396,
              40.43160350723965
            ]
          ]
        ]
      },
      {
        "type": "Polygon",
        "coordinates": [
          [
            [
              -111.91721073713632,
              40.43151559515174
            ],
            [
              -111.91721073713632,
              40.43131779295394
            ],
            [
              -111.91758159873396,
              40.43131779295394
            ],
            [
              -111.91758159873396,
              40.43151559515174
            ],
            [
              -111.91721073713632,
              40.43151559515174
            ]
          ]
        ]
      },
      {
        "type": "Polygon",
        "coordinates": [
          [
            [
              -111.91910113739277,
              40.432069551195696
            ],
            [
              -111.91910113739277,
              40.4322673533935
            ],
            [
              -111.91873027579513,
              40.4322673533935
            ],
            [
              -111.91873027579513,
              40.432069551195696
            ],
            [
              -111.91910113739277,
              40.432069551195696
            ]
          ]
        ]
      },
      {
        "type": "Polygon",
        "coordinates": [
          [
            [
              -111.91873027579513,
              40.43198163910778
            ],
            [
              -111.91873027579513,
              40.43178383690998
            ],
            [
              -111.91910113739277,
              40.43178383690998
            ],
            [
              -111.91910113739277,
              40.43198163910778
            ],
            [
              -111.91873027579513,
              40.43198163910778
            ]
          ]
        ]
      },
      {
        "type": "Polygon",
        "coordinates": [
          [
            [
              -111.91835941419748,
              40.43198163910778
            ],
            [
              -111.91835941419748,
              40.43178383690998
            ],
            [
              -111.91873027579513,
              40.43178383690998
            ],
            [
              -111.91873027579513,
              40.43198163910778
            ],
            [
              -111.91835941419748,
              40.43198163910778
            ]
          ]
        ]
      },
      {
        "type": "Polygon",
        "coordinates": [
          [
            [
              -111.91721073713632,
              40.43198163910778
            ],
            [
              -111.91721073713632,
              40.43178383690998
            ],
            [
              -111.91758159873396,
              40.43178383690998
            ],
            [
              -111.91758159873396,
              40.43198163910778
            ],
            [
              -111.91721073713632,
              40.43198163910778
            ]
          ]
        ]
      },
      {
        "type": "Polygon",
        "coordinates": [
          [
            [
              -111.91842950646571,
              40.43225861712976
            ],
            [
              -111.91835941419748,
              40.43225861712976
            ],
            [
              -111.91835941419748,
              40.432069551195696
            ],
            [
              -111.91873027579513,
              40.432069551195696
            ],
            [
              -111.91873027579513,
              40.4322673533935
            ],
            [
              -111.91842950646571,
              40.4322673533935
            ],
            [
              -111.91842950646571,
              40.43225861712976
            ]
          ]
        ]
      },
      {
        "type": "Polygon",
        "coordinates": [
          [
            [
              -111.91758159873396,
              40.432069551195696
            ],
            [
              -111.91758159873396,
              40.43225861712976
            ],
            [
              -111.91751150646573,
              40.43225861712976
            ],
            [
              -111.91751150646573,
              40.4322673533935
            ],
            [
              -111.91721073713632,
              40.4322673533935
            ],
            [
              -111.91721073713632,
              40.432069551195696
            ],
            [
              -111.91758159873396,
              40.432069551195696
            ]
          ]
        ]
      },
      {
        "type": "Polygon",
        "coordinates": [
          [
            [
              -111.91910113739277,
              40.43253559515174
            ],
            [
              -111.91910113739277,
              40.432733397349544
            ],
            [
              -111.91876171270242,
              40.432733397349544
            ],
            [
              -111.91876171270242,
              40.43253559515174
            ],
            [
              -111.91910113739277,
              40.43253559515174
            ]
          ]
        ]
      },
      {
        "type": "Polygon",
        "coordinates": [
          [
            [
              -111.91876171270242,
              40.43244768306383
            ],
            [
              -111.91876171270242,
              40.432249880866024
            ],
            [
              -111.91910113739277,
              40.432249880866024
            ],
            [
              -111.91910113739277,
              40.43244768306383
            ],
            [
              -111.91876171270242,
              40.43244768306383
            ]
          ]
        ]
      },
      {
        "type": "Polygon",
        "coordinates": [
          [
            [
              -111.91717930022902,
              40.43253559515174
            ],
            [
              -111.91717930022902,
              40.432733397349544
            ],
            [
              -111.91683987553867,
              40.432733397349544
            ],
            [
              -111.91683987553867,
              40.43253559515174
            ],
            [
              -111.91717930022902,
              40.43253559515174
            ]
          ]
        ]
      },
      {
        "type": "Polygon",
        "coordinates": [
          [
            [
              -111.91683987553867,
              40.43244768306383
            ],
            [
              -111.91683987553867,
              40.432249880866024
            ],
            [
              -111.91717930022902,
              40.432249880866024
            ],
            [
              -111.91717930022902,
              40.43244768306383
            ],
            [
              -111.91683987553867,
              40.43244768306383
            ]
          ]
        ]
      },
      {
        "type": "Polygon",
        "coordinates": [
          [
            [
              -111.91910113739277,
              40.433001639107786
            ],
            [
              -111.91910113739277,
              40.43319944130558
            ],
            [
              -111.91876171270242,
              40.43319944130558
            ],
            [
              -111.91876171270242,
              40.433001639107786
            ],
            [
              -111.91910113739277,
              40.433001639107786
            ]
          ]
        ]
      },
      {
        "type": "Polygon",
        "coordinates": [
          [
            [
              -111.91876171270242,
              40.43291372701987
            ],
            [
              -111.91876171270242,
              40.43271592482207
            ],
            [
              -111.91910113739277,
              40.43271592482207
            ],
            [
              -111.91910113739277,
              40.43291372701987
            ],
            [
              -111.91876171270242,
              40.43291372701987
            ]
          ]
        ]
      },
      {
        "type": "Polygon",
        "coordinates": [
          [
            [
              -111.91717930022902,
              40.433001639107786
            ],
            [
              -111.91717930022902,
              40.43319944130558
            ],
            [
              -111.91683987553867,
              40.43319944130558
            ],
            [
              -111.91683987553867,
              40.433001639107786
            ],
            [
              -111.91717930022902,
              40.433001639107786
            ]
          ]
        ]
      },
      {
        "type": "Polygon",
        "coordinates": [
          [
            [
              -111.91683987553867,
              40.43291372701987
            ],
            [
              -111.91683987553867,
              40.43271592482207
            ],
            [
              -111.91717930022902,
              40.43271592482207
            ],
            [
              -111.91717930022902,
              40.43291372701987
            ],
            [
              -111.91683987553867,
              40.43291372701987
            ]
          ]
        ]
      },
      {
        "type": "Polygon",
        "coordinates": [
          [
            [
              -111.91842228801207,
              40.43225861712976
            ],
            [
              -111.91842228801207,
              40.432249880866024
            ],
            [
              -111.91876171270242,
              40.432249880866024
            ],
            [
              -111.91876171270242,
              40.43244768306383
            ],
            [
              -111.91842950646571,
              40.43244768306383
            ],
            [
              -111.91842950646571,
              40.43225861712976
            ],
            [
              -111.91842228801207,
              40.43225861712976
            ]
          ]
        ]
      },
      {
        "type": "Polygon",
        "coordinates": [
          [
            [
              -111.91751150646573,
              40.43225861712976
            ],
            [
              -111.91751150646573,
              40.43244768306383
            ],
            [
              -111.91717930022902,
              40.43244768306383
            ],
            [
              -111.91717930022902,
              40.432249880866024
            ],
            [
              -111.91751872491938,
              40.432249880866024
            ],
            [
              -111.91751872491938,
              40.43225861712976
            ],
            [
              -111.91751150646573,
              40.43225861712976
            ]
          ]
        ]
      },
      {
        "type": "Polygon",
        "coordinates": [
          [
            [
              -111.91842950646571,
              40.43253559515174
            ],
            [
              -111.91876171270242,
              40.43253559515174
            ],
            [
              -111.91876171270242,
              40.432733397349544
            ],
            [
              -111.91842950646571,
              40.432733397349544
            ],
            [
              -111.91842950646571,
              40.43253559515174
            ]
          ]
        ]
      },
      {
        "type": "Polygon",
        "coordinates": [
          [
            [
              -111.91751150646573,
              40.43253559515174
            ],
            [
              -111.91751150646573,
              40.432733397349544
            ],
            [
              -111.91717930022902,
              40.432733397349544
            ],
            [
              -111.91717930022902,
              40.43253559515174
            ],
            [
              -111.91751150646573,
              40.43253559515174
            ]
          ]
        ]
      },
      {
        "type": "Polygon",
        "coordinates": [
          [
            [
              -111.91842950646571,
              40.433001639107786
            ],
            [
              -111.91876171270242,
              40.433001639107786
            ],
            [
              -111.91876171270242,
              40.43319944130558
            ],
            [
              -111.91842950646571,
              40.43319944130558
            ],
            [
              -111.91842950646571,
              40.433001639107786
            ]
          ]
        ]
      },
      {
        "type": "Polygon",
        "coordinates": [
          [
            [
              -111.91842950646571,
              40.43291372701987
            ],
            [
              -111.91842950646571,
              40.43271592482207
            ],
            [
              -111.91876171270242,
              40.43271592482207
            ],
            [
              -111.91876171270242,
              40.43291372701987
            ],
            [
              -111.91842950646571,
              40.43291372701987
            ]
          ]
        ]
      },
      {
        "type": "Polygon",
        "coordinates": [
          [
            [
              -111.91751150646573,
              40.433001639107786
            ],
            [
              -111.91751150646573,
              40.43319944130558
            ],
            [
              -111.91717930022902,
              40.43319944130558
            ],
            [
              -111.91717930022902,
              40.433001639107786
            ],
            [
              -111.91751150646573,
              40.433001639107786
            ]
          ]
        ]
      },
      {
        "type": "Polygon",
        "coordinates": [
          [
            [
              -111.91751150646573,
              40.43291372701987
            ],
            [
              -111.91717930022902,
              40.43291372701987
            ],
            [
              -111.91717930022902,
              40.43271592482207
            ],
            [
              -111.91751150646573,
              40.43271592482207
            ],
            [
              -111.91751150646573,
              40.43291372701987
            ]
          ]
        ]
      },
      {
        "type": "Polygon",
        "coordinates": [
          [
            [
              -111.91802825409489,
              40.43160350723965
            ],
            [
              -111.91835941419748,
              40.43160350723965
            ],
            [
              -111.91835941419748,
              40.43180130943745
            ],
            [
              -111.91802825409489,
              40.43180130943745
            ],
            [
              -111.91802825409489,
              40.43160350723965
            ]
          ]
        ]
      },
      {
        "type": "Polygon",
        "coordinates": [
          [
            [
              -111.91802825409489,
              40.43198163910778
            ],
            [
              -111.91802825409489,
              40.43178383690998
            ],
            [
              -111.91835941419748,
              40.43178383690998
            ],
            [
              -111.91835941419748,
              40.43198163910778
            ],
            [
              -111.91802825409489,
              40.43198163910778
            ]
          ]
        ]
      },
      {
        "type": "Polygon",
        "coordinates": [
          [
            [
              -111.91791275883655,
              40.43160350723965
            ],
            [
              -111.91791275883655,
              40.43180130943745
            ],
            [
              -111.91758159873396,
              40.43180130943745
            ],
            [
              -111.91758159873396,
              40.43160350723965
            ],
            [
              -111.91791275883655,
              40.43160350723965
            ]
          ]
        ]
      },
      {
        "type": "Polygon",
        "coordinates": [
          [
            [
              -111.91791275883655,
              40.43198163910778
            ],
            [
              -111.91758159873396,
              40.43198163910778
            ],
            [
              -111.91758159873396,
              40.43178383690998
            ],
            [
              -111.91791275883655,
              40.43178383690998
            ],
            [
              -111.91791275883655,
              40.43198163910778
            ]
          ]
        ]
      },
      {
        "type": "Polygon",
        "coordinates": [
          [
            [
              -111.91802825409489,
              40.43225861712976
            ],
            [
              -111.91802825409489,
              40.432069551195696
            ],
            [
              -111.91835941419748,
              40.432069551195696
            ],
            [
              -111.91835941419748,
              40.43225861712976
            ],
            [
              -111.91802825409489,
              40.43225861712976
            ]
          ]
        ]
      },
      {
        "type": "Polygon",
        "coordinates": [
          [
            [
              -111.91791275883655,
              40.432069551195696
            ],
            [
              -111.91791275883655,
              40.43225861712976
            ],
            [
              -111.91758159873396,
              40.43225861712976
            ],
            [
              -111.91758159873396,
              40.432069551195696
            ],
            [
              -111.91791275883655,
              40.432069551195696
            ]
          ]
        ]
      }
    ],
    "road_geometries": [
      {
        "type": "LineString",
        "coordinates": [
          [
            -111.91797050646572,
            40.43109350723965
          ],
          [
            -111.91797050646572,
            40.432264111635256
          ]
        ]
      },
      {
        "type": "LineString",
        "coordinates": [
          [
            -111.91910113739277,
            40.4315595511957
          ],
          [
            -111.91798855259984,
            40.4315595511957
          ]
        ]
      },
      {
        "type": "LineString",
        "coordinates": [
          [
            -111.9179524603316,
            40.4315595511957
          ],
          [
            -111.91683987553867,
            40.4315595511957
          ]
        ]
      },
      {
        "type": "LineString",
        "coordinates": [
          [
            -111.91910113739277,
            40.43202559515174
          ],
          [
            -111.91798855259984,
            40.43202559515174
          ]
        ]
      },
      {
        "type": "LineString",
        "coordinates": [
          [
            -111.9179524603316,
            40.43202559515174
          ],
          [
            -111.91683987553867,
            40.43202559515174
          ]
        ]
      },
      {
        "type": "LineString",
        "coordinates": [
          [
            -111.91910113739277,
            40.43249163910778
          ],
          [
            -111.91842228801207,
            40.43249163910778
          ]
        ]
      },
      {
        "type": "LineString",
        "coordinates": [
          [
            -111.91751872491938,
            40.43249163910778
          ],
          [
            -111.91683987553867,
            40.43249163910778
          ]
        ]
      },
      {
        "type": "LineString",
        "coordinates": [
          [
            -111.91910113739277,
            40.432957683063826
          ],
          [
            -111.91842228801207,
            40.432957683063826
          ]
        ]
      },
      {
        "type": "LineString",
        "coordinates": [
          [
            -111.91751872491938,
            40.432957683063826
          ],
          [
            -111.91683987553867,
            40.432957683063826
          ]
        ]
      }
    ],
    "open_space_area_sqft": 540912.1399972253,
    "utility_length_ft": 0.0,
    "score": null,
    "buildable_area_sqft": null,
    "metadata": {
      "source_engine": "bedrock.layout_service",
      "source_run_id": null,
      "observed_at": "2026-03-20T17:53:56.294492Z"
    }
  },
  "feasibility_result": {
    "schema_name": "FeasibilityResult",
    "schema_version": "1.0.0",
    "scenario_id": "a0377686-d2ec-5e1f-a85d-9b1e67ac8ecd",
    "layout_id": "layout-exp-lehi-007-determinism-1-3dbe4eddc3eb",
    "parcel_id": "exp-lehi-007-determinism-1",
    "units": 40,
    "estimated_home_price": 480000.0,
    "construction_cost_per_home": 406089.78910500003,
    "development_cost_total": 1159312.4132231404,
    "projected_revenue": 19200000.0,
    "projected_cost": 17402903.977423143,
    "projected_profit": 1797096.0225768574,
    "ROI": 0.10326414631191652,
    "profit_margin": 0.09359875117587799,
    "revenue_per_unit": 480000.0,
    "cost_per_unit": 435072.59943557857,
    "rank": null,
    "risk_score": 0.5474995747219793,
    "requested_units": null,
    "constraint_violations": [],
    "confidence": 0.9,
    "status": "feasible",
    "financial_summary": {
      "units": 40,
      "estimated_home_price": 480000.0,
      "construction_cost_per_home": 406089.78910500003,
      "road_cost_per_ft": 300.0,
      "road_length": 2411.5,
      "land_cost": 0.0,
      "projected_revenue": 19200000.0,
      "development_cost_total": 1159312.4132231404,
      "projected_cost": 17402903.977423143,
      "projected_profit": 1797096.0225768574,
      "ROI": 0.10326414631191652,
      "development_cost_breakdown": {
        "roads": 723450.0,
        "utilities": 0.0,
        "grading": 72345.0,
        "sitework": 223517.4132231405,
        "permitting": 140000.0
      },
      "profit_margin": 0.09359875117587799,
      "revenue_per_unit": 480000.0,
      "cost_per_unit": 435072.59943557857
    },
    "explanation": {
      "primary_driver": "road_cost",
      "cost_breakdown": {
        "construction": 16243591.5642,
        "development": 1159312.4132231404
      },
      "revenue_breakdown": {
        "units": 40,
        "price_per_home": 480000.0
      }
    },
    "assumptions": {
      "used_default_estimated_home_price": true,
      "used_default_construction_cost_per_home": true,
      "used_default_road_cost_per_ft": true,
      "used_default_land_price": true,
      "used_default_soft_cost_factor": true
    },
    "metadata": null
  },
  "timestamp": "2026-03-20T17:53:56.294870Z",
  "git_commit": null,
  "input_hash": null,
  "stage_runtimes": {}
}