{
  "schema_name": "PipelineRun",
  "schema_version": "1.0.0",
  "run_id": "e3e8ba29-d3ef-4d2b-8a7a-1068410efe55",
  "status": "completed",
  "parcel_id": "ut-salt-lake-71",
  "zoning_result": {
    "schema_name": "ZoningRules",
    "schema_version": "1.0.0",
    "parcel_id": "ut-salt-lake-71",
    "jurisdiction": "Salt Lake City",
    "district": "R-1-7000",
    "district_id": null,
    "description": null,
    "overlays": [],
    "standards": [
      {
        "id": "R-1-7000:min_lot_size_sqft",
        "district_id": null,
        "standard_type": "min_lot_size_sqft",
        "value": 7000.0,
        "units": "sqft",
        "conditions": [],
        "citation": null,
        "metadata": {
          "source_engine": "zoning_data_scraper",
          "source_run_id": "jurisdiction_fallback",
          "observed_at": "2026-03-26T23:09:26.190484Z"
        }
      },
      {
        "id": "R-1-7000:max_units_per_acre",
        "district_id": null,
        "standard_type": "max_units_per_acre",
        "value": 6.22,
        "units": "du/ac",
        "conditions": [],
        "citation": null,
        "metadata": {
          "source_engine": "zoning_data_scraper",
          "source_run_id": "jurisdiction_fallback",
          "observed_at": "2026-03-26T23:09:26.190484Z"
        }
      },
      {
        "id": "R-1-7000:height_limit_ft",
        "district_id": null,
        "standard_type": "height_limit_ft",
        "value": 35.0,
        "units": "ft",
        "conditions": [],
        "citation": null,
        "metadata": {
          "source_engine": "zoning_data_scraper",
          "source_run_id": "jurisdiction_fallback",
          "observed_at": "2026-03-26T23:09:26.190484Z"
        }
      },
      {
        "id": "R-1-7000:lot_coverage_max",
        "district_id": null,
        "standard_type": "lot_coverage_max",
        "value": 0.45,
        "units": null,
        "conditions": [],
        "citation": null,
        "metadata": {
          "source_engine": "zoning_data_scraper",
          "source_run_id": "jurisdiction_fallback",
          "observed_at": "2026-03-26T23:09:26.190484Z"
        }
      },
      {
        "id": "R-1-7000:min_frontage_ft",
        "district_id": null,
        "standard_type": "min_frontage_ft",
        "value": 50.0,
        "units": "ft",
        "conditions": [],
        "citation": null,
        "metadata": {
          "source_engine": "zoning_data_scraper",
          "source_run_id": "jurisdiction_fallback",
          "observed_at": "2026-03-26T23:09:26.190484Z"
        }
      },
      {
        "id": "R-1-7000:front_setback_ft",
        "district_id": null,
        "standard_type": "front_setback_ft",
        "value": 25.0,
        "units": "ft",
        "conditions": [],
        "citation": null,
        "metadata": {
          "source_engine": "zoning_data_scraper",
          "source_run_id": "jurisdiction_fallback",
          "observed_at": "2026-03-26T23:09:26.190484Z"
        }
      },
      {
        "id": "R-1-7000:side_setback_ft",
        "district_id": null,
        "standard_type": "side_setback_ft",
        "value": 8.0,
        "units": "ft",
        "conditions": [],
        "citation": null,
        "metadata": {
          "source_engine": "zoning_data_scraper",
          "source_run_id": "jurisdiction_fallback",
          "observed_at": "2026-03-26T23:09:26.190484Z"
        }
      },
      {
        "id": "R-1-7000:rear_setback_ft",
        "district_id": null,
        "standard_type": "rear_setback_ft",
        "value": 20.0,
        "units": "ft",
        "conditions": [],
        "citation": null,
        "metadata": {
          "source_engine": "zoning_data_scraper",
          "source_run_id": "jurisdiction_fallback",
          "observed_at": "2026-03-26T23:09:26.190484Z"
        }
      }
    ],
    "setbacks": {
      "front": 25.0,
      "side": 8.0,
      "rear": 20.0
    },
    "min_lot_size_sqft": 7000.0,
    "max_units_per_acre": 6.22,
    "height_limit_ft": 35.0,
    "lot_coverage_max": 0.45,
    "min_frontage_ft": 50.0,
    "road_right_of_way_ft": null,
    "allowed_uses": [
      "single_family_residential"
    ],
    "citations": [],
    "metadata": {
      "source_engine": "zoning_data_scraper",
      "source_run_id": "jurisdiction_fallback",
      "observed_at": "2026-03-26T23:09:26.190484Z"
    }
  },
  "layout_result": {
    "schema_name": "LayoutResult",
    "schema_version": "1.0.0",
    "layout_id": "layout-ut-salt-lake-71-3ff18e284270",
    "parcel_id": "ut-salt-lake-71",
    "unit_count": 10,
    "road_length_ft": 706.1,
    "lot_geometries": [
      {
        "type": "Polygon",
        "coordinates": [
          [
            [
              -111.903885,
              40.795779
            ],
            [
              -111.903813,
              40.795779
            ],
            [
              -111.903813,
              40.795436
            ],
            [
              -111.904065,
              40.795436
            ],
            [
              -111.904065,
              40.795646
            ],
            [
              -111.903885,
              40.795779
            ]
          ]
        ]
      },
      {
        "type": "Polygon",
        "coordinates": [
          [
            [
              -111.903571,
              40.795355
            ],
            [
              -111.903571,
              40.795154
            ],
            [
              -111.904024,
              40.795154
            ],
            [
              -111.904024,
              40.795355
            ],
            [
              -111.903571,
              40.795355
            ]
          ]
        ]
      },
      {
        "type": "Polygon",
        "coordinates": [
          [
            [
              -111.904024,
              40.795009
            ],
            [
              -111.904024,
              40.795154
            ],
            [
              -111.903571,
              40.795154
            ],
            [
              -111.903571,
              40.794913
            ],
            [
              -111.903901,
              40.794913
            ],
            [
              -111.904024,
              40.795009
            ]
          ]
        ]
      },
      {
        "type": "Polygon",
        "coordinates": [
          [
            [
              -111.903813,
              40.795436
            ],
            [
              -111.903813,
              40.795779
            ],
            [
              -111.90356,
              40.795779
            ],
            [
              -111.90356,
              40.795436
            ],
            [
              -111.903813,
              40.795436
            ]
          ]
        ]
      },
      {
        "type": "Polygon",
        "coordinates": [
          [
            [
              -111.90356,
              40.795436
            ],
            [
              -111.90356,
              40.795779
            ],
            [
              -111.903307,
              40.795779
            ],
            [
              -111.903307,
              40.795436
            ],
            [
              -111.90356,
              40.795436
            ]
          ]
        ]
      },
      {
        "type": "Polygon",
        "coordinates": [
          [
            [
              -111.903303,
              40.794671
            ],
            [
              -111.903464,
              40.794671
            ],
            [
              -111.903464,
              40.794913
            ],
            [
              -111.903011,
              40.794913
            ],
            [
              -111.903011,
              40.794886
            ],
            [
              -111.903303,
              40.794671
            ]
          ]
        ]
      },
      {
        "type": "Polygon",
        "coordinates": [
          [
            [
              -111.903464,
              40.795154
            ],
            [
              -111.903011,
              40.795154
            ],
            [
              -111.903011,
              40.794913
            ],
            [
              -111.903464,
              40.794913
            ],
            [
              -111.903464,
              40.795154
            ]
          ]
        ]
      },
      {
        "type": "Polygon",
        "coordinates": [
          [
            [
              -111.903464,
              40.795355
            ],
            [
              -111.903011,
              40.795355
            ],
            [
              -111.903011,
              40.795154
            ],
            [
              -111.903464,
              40.795154
            ],
            [
              -111.903464,
              40.795355
            ]
          ]
        ]
      },
      {
        "type": "Polygon",
        "coordinates": [
          [
            [
              -111.903307,
              40.795436
            ],
            [
              -111.903307,
              40.795779
            ],
            [
              -111.903054,
              40.795779
            ],
            [
              -111.903054,
              40.795436
            ],
            [
              -111.903307,
              40.795436
            ]
          ]
        ]
      },
      {
        "type": "Polygon",
        "coordinates": [
          [
            [
              -111.902839,
              40.795012
            ],
            [
              -111.903054,
              40.795012
            ],
            [
              -111.903054,
              40.795355
            ],
            [
              -111.902802,
              40.795355
            ],
            [
              -111.902802,
              40.795039
            ],
            [
              -111.902839,
              40.795012
            ]
          ]
        ]
      }
    ],
    "road_geometries": [
      {
        "type": "LineString",
        "coordinates": [
          [
            -111.904318,
            40.795396
          ],
          [
            -111.902802,
            40.795396
          ]
        ]
      },
      {
        "type": "LineString",
        "coordinates": [
          [
            -111.903518,
            40.794604
          ],
          [
            -111.903518,
            40.794671
          ]
        ]
      },
      {
        "type": "LineString",
        "coordinates": [
          [
            -111.903518,
            40.794671
          ],
          [
            -111.903518,
            40.795396
          ]
        ]
      }
    ],
    "open_space_area_sqft": 160821.24999910648,
    "utility_length_ft": 0.0,
    "score": null,
    "buildable_area_sqft": null,
    "metadata": {
      "source_engine": "bedrock.layout_service",
      "source_run_id": null,
      "observed_at": "2026-03-26T23:09:26.544966Z"
    }
  },
  "feasibility_result": {
    "schema_name": "FeasibilityResult",
    "schema_version": "1.0.0",
    "scenario_id": "321536a0-fe82-5113-8a78-eb6981e4348f",
    "layout_id": "layout-ut-salt-lake-71-3ff18e284270",
    "parcel_id": "ut-salt-lake-71",
    "units": 10,
    "estimated_home_price": 480000.0,
    "construction_cost_per_home": 449280.00000000006,
    "development_cost_total": 334468.06198347104,
    "projected_revenue": 4800000.0,
    "projected_cost": 4827268.061983472,
    "projected_profit": -27268.061983471736,
    "ROI": -0.0056487565292298245,
    "profit_margin": -0.005680846246556612,
    "revenue_per_unit": 480000.0,
    "cost_per_unit": 482726.8061983472,
    "rank": null,
    "risk_score": 0.6742505326389756,
    "requested_units": null,
    "constraint_violations": [
      "projected_profit_negative"
    ],
    "confidence": 0.9,
    "status": "constrained",
    "financial_summary": {
      "units": 10,
      "estimated_home_price": 480000.0,
      "construction_cost_per_home": 449280.00000000006,
      "road_cost_per_ft": 300.0,
      "road_length": 706.1,
      "land_cost": 0.0,
      "projected_revenue": 4800000.0,
      "development_cost_total": 334468.06198347104,
      "projected_cost": 4827268.061983472,
      "projected_profit": -27268.061983471736,
      "ROI": -0.0056487565292298245,
      "development_cost_breakdown": {
        "roads": 211830.0,
        "utilities": 0.0,
        "grading": 21183.0,
        "sitework": 66455.06198347107,
        "permitting": 35000.0
      },
      "profit_margin": -0.005680846246556612,
      "revenue_per_unit": 480000.0,
      "cost_per_unit": 482726.8061983472
    },
    "explanation": {
      "primary_driver": "home_price",
      "cost_breakdown": {
        "construction": 4492800.000000001,
        "development": 334468.06198347104
      },
      "revenue_breakdown": {
        "units": 10,
        "price_per_home": 480000.0
      }
    },
    "assumptions": {
      "used_default_estimated_home_price": true,
      "used_default_construction_cost_per_home": true,
      "used_default_road_cost_per_ft": true,
      "used_default_land_price": true,
      "used_default_soft_cost_factor": true
    },
    "metadata": null
  },
  "near_feasible_result": null,
  "timestamp": "2026-03-26T23:09:26.545275Z",
  "git_commit": "05222bb8c8c582cae630ed93bacc9765ba243990",
  "input_hash": "a3c375a540fb16b15997a57d70b8a08dab6fde780f501f3214cafb0c3e9d394b",
  "stage_runtimes": {
    "parcel.load": 0.002394,
    "zoning.lookup": 0.023305,
    "layout.search": 0.353847,
    "feasibility.evaluate": 0.00025
  },
  "zoning_bypassed": false,
  "bypass_reason": null
}